countryguess/__init__.py
countryguess/__main__.py
countryguess/_cli.py
countryguess/_countrydata.json
countryguess/_countrydata.py
countryguess/_guess_country.py
countryguess-0.4.9.dist-info/licenses/LICENSE
countryguess-0.4.9.dist-info/METADATA
countryguess-0.4.9.dist-info/WHEEL
countryguess-0.4.9.dist-info/entry_points.txt
countryguess-0.4.9.dist-info/top_level.txt
countryguess-0.4.9.dist-info/RECORD
