Metadata-Version: 2.4
Name: countryguess
Version: 0.4.9
Summary: Fuzzy lookup of country information
Author-email: plotski <plotski@example.org>
License-Expression: GPL-3.0-or-later
Project-URL: Repository, https://codeberg.org/plotski/countryguess
Project-URL: Bug Tracker, https://codeberg.org/plotski/countryguess/issues
Project-URL: Changelog, https://codeberg.org/plotski/countryguess/raw/branch/master/NEWS
Keywords: country,countries,search,fuzzy,iso3166
Classifier: Programming Language :: Python :: 3
Requires-Python: >=3.9
License-File: LICENSE
Provides-Extra: dev
Requires-Dist: pytest; extra == "dev"
Requires-Dist: tox; extra == "dev"
Requires-Dist: coverage; extra == "dev"
Requires-Dist: pytest-cov; extra == "dev"
Requires-Dist: pytest-mock; extra == "dev"
Requires-Dist: ruff; extra == "dev"
Requires-Dist: flake8; extra == "dev"
Requires-Dist: isort; extra == "dev"
Dynamic: license-file
